uxid/__init__.py
uxid/__version__.py
uxid-0.0.1.dist-info/LICENSE
uxid-0.0.1.dist-info/METADATA
uxid-0.0.1.dist-info/WHEEL
uxid-0.0.1.dist-info/top_level.txt
uxid-0.0.1.dist-info/RECORD
